opticalpyber/__init__.py
opticalpyber/optical_fiber.py
opticalpyber/planar_waveguide.py
opticalpyber/retangular_waveguide.py
opticalpyber/waveguide.py
opticalpyber-0.0.1.dist-info/LICENSE
opticalpyber-0.0.1.dist-info/METADATA
opticalpyber-0.0.1.dist-info/WHEEL
opticalpyber-0.0.1.dist-info/top_level.txt
opticalpyber-0.0.1.dist-info/RECORD
