Metadata-Version: 2.1
Name: opticalpyber
Version: 0.0.1
Summary: Package with tools to waveguides and optical fibers
Home-page: https://github.com/marcos-moura97/opticalpyber
Author: Marcos Moura
Author-email: gabbyru2@gmail.com
License: UNKNOWN
Platform: UNKNOWN
Classifier: Programming Language :: Python :: 3
Classifier: Intended Audience :: Science/Research
Classifier: License :: OSI Approved :: BSD License
Classifier: Operating System :: OS Independent
License-File: LICENSE
Requires-Dist: numpy
Requires-Dist: scipy
